[{"Candidate Name":"Gregory Cendana ","Contributor":"Lepham, Nicholas","Address":"3706 Massachusetts Ave., NW","city":"Washington","state":"DC","Zip":"20016","Contribution Type":"paypal","Amount":50.0,"Date of Receipt":"8\/31\/2012"},{"Candidate Name":"Gregory Cendana ","Contributor":"Berkley, Carmen ","Address":"4000 Massachusetts Ave., NW","city":"Washington","state":"DC","Zip":"20016","Contribution Type":"Paypal","Amount":20.0,"Date of Receipt":"8\/31\/2012"},{"Candidate Name":"Gregory Cendana ","Contributor":"Lagna, Jason","Address":"n\/a","city":"n\/a","state":null,"Zip":"00000","Contribution Type":"Paypal","Amount":5.0,"Date of Receipt":"8\/31\/2012"},{"Candidate Name":"Gregory Cendana ","Contributor":"Shirma, Darren","Address":"n\/a","city":"n\/a","state":null,"Zip":"00000","Contribution Type":"Paypal","Amount":50.0,"Date of Receipt":"8\/31\/2012"},{"Candidate Name":"Gregory Cendana ","Contributor":"Garcia, Martin","Address":"1912 9th St., NW #2","city":"Washington","state":"DC","Zip":"20001","Contribution Type":"Check","Amount":100.0,"Date of Receipt":"3\/11\/2012"},{"Candidate Name":"Gregory Cendana ","Contributor":"Malik, Samar","Address":"2505 13th St., NW #303","city":"Washington","state":"DC","Zip":"20009","Contribution Type":"Check","Amount":20.0,"Date of Receipt":"3\/11\/2012"},{"Candidate Name":"Gregory Cendana ","Contributor":"Witin, Tiffany","Address":"n\/a","city":"washington","state":"DC","Zip":"00000","Contribution Type":"Check","Amount":20.0,"Date of Receipt":"3\/11\/2012"},{"Candidate Name":"Gregory Cendana ","Contributor":"Peoples, Angela","Address":"n\/a","city":"Washington","state":"DC","Zip":"00000","Contribution Type":"Check","Amount":75.0,"Date of Receipt":"3\/11\/2012"},{"Candidate Name":"Gregory Cendana ","Contributor":"Thammarath, Monica","Address":"3213 Sherman Ave., NW","city":"Washington","state":"DC","Zip":"20010","Contribution Type":"Check","Amount":100.0,"Date of Receipt":"3\/11\/2012"},{"Candidate Name":"Gregory Cendana ","Contributor":"Wasserman, Rebecca","Address":"1375 Fairmont St., NW #509","city":"Washington","state":"DC","Zip":"20009","Contribution Type":"Check","Amount":75.0,"Date of Receipt":"3\/11\/2012"},{"Candidate Name":"Gregory Cendana ","Contributor":"Holt, Frances","Address":"1508 Missouri Ave., NW","city":"Washington ","state":"DC","Zip":"20011","Contribution Type":"Check","Amount":50.0,"Date of Receipt":"3\/11\/2012"},{"Candidate Name":"Gregory Cendana ","Contributor":"Villano, Vincent","Address":"2011-A 1st NW","city":"Washington","state":"DC","Zip":"20001","Contribution Type":"Check","Amount":50.0,"Date of Receipt":"3\/11\/2012"},{"Candidate Name":"Gregory Cendana ","Contributor":"Cendana, Jessica","Address":"1810 California St., NW #5","city":"Washington","state":"DC","Zip":"20001","Contribution Type":"Check","Amount":100.0,"Date of Receipt":"3\/11\/2012"},{"Candidate Name":"Gregory Cendana ","Contributor":"Seebory, Scott","Address":"n\/a","city":"Washington","state":"DC","Zip":"00000","Contribution Type":"Check","Amount":25.0,"Date of Receipt":"3\/11\/2012"},{"Candidate Name":"Gregory Cendana ","Contributor":"Cook, Kurston","Address":"3919 New hampshire Ave., NW","city":"Washington","state":"DC","Zip":"20011","Contribution Type":"Check","Amount":45.0,"Date of Receipt":"3\/11\/2012"},{"Candidate Name":"Gregory Cendana ","Contributor":"Sloan, Christopher","Address":"3624 Connecticut Ave., NW #5","city":"Washington","state":"DC","Zip":"20008","Contribution Type":"Check","Amount":50.0,"Date of Receipt":"3\/11\/2012"},{"Candidate Name":"Gregory Cendana ","Contributor":"Chow, Olivia","Address":"1920 10th St., NW #5","city":"Washington","state":"DC","Zip":"20001","Contribution Type":"Check","Amount":20.0,"Date of Receipt":"3\/11\/2012"},{"Candidate Name":"Gregory Cendana ","Contributor":"Rubino, Jullian","Address":"n\/a","city":"Washington","state":"DC","Zip":"00000","Contribution Type":"Check","Amount":25.0,"Date of Receipt":"3\/11\/2012"},{"Candidate Name":"Gregory Cendana ","Contributor":"Shuler, Elizabeth","Address":"4915 46th St., NW","city":"Washington","state":"DC","Zip":"20016","Contribution Type":"Check","Amount":50.0,"Date of Receipt":"3\/11\/2012"},{"Candidate Name":"Gregory Cendana ","Contributor":"Cendana, Maria","Address":"8825 Catfish Ct.","city":"Elk Grove ","state":"CA","Zip":"95624","Contribution Type":"Paypal","Amount":100.0,"Date of Receipt":"3\/11\/2012"},{"Candidate Name":"Gregory Cendana ","Contributor":"Chinn, Susan","Address":"n\/a","city":"Washington","state":"DC","Zip":"00000","Contribution Type":"Paypal","Amount":25.0,"Date of Receipt":"3\/11\/2012"},{"Candidate Name":"Gregory Cendana ","Contributor":"Totten, Gloria","Address":"n\/a","city":"Washington","state":"DC","Zip":"20000","Contribution Type":"Paypal","Amount":100.0,"Date of Receipt":"3\/11\/2012"},{"Candidate Name":"Gregory Cendana ","Contributor":"DeLacruz, Carlo","Address":"n\/a","city":"Washington","state":"DC","Zip":"00000","Contribution Type":"Paypal","Amount":40.0,"Date of Receipt":"3\/11\/2012"},{"Candidate Name":"Gregory Cendana ","Contributor":"Chan, Kristy","Address":"n\/a","city":"Washington","state":"DC","Zip":"00000","Contribution Type":"Paypal","Amount":50.0,"Date of Receipt":"3\/11\/2012"},{"Candidate Name":"Gregory Cendana ","Contributor":"Etcubanez, Marita","Address":"n\/a","city":"Washington","state":"DC","Zip":"00000","Contribution Type":"Paypal","Amount":50.0,"Date of Receipt":"3\/11\/2012"},{"Candidate Name":"Gregory Cendana ","Contributor":"Saunders, Terry","Address":"n\/a","city":"washington","state":"DC","Zip":"00000","Contribution Type":"Paypal","Amount":50.0,"Date of Receipt":"3\/11\/2012"},{"Candidate Name":"Gregory Cendana ","Contributor":"Jimenez, Mark","Address":"n\/a","city":"Washington","state":"DC","Zip":"00000","Contribution Type":"Paypal","Amount":20.0,"Date of Receipt":"3\/11\/2012"},{"Candidate Name":"Gregory Cendana ","Contributor":"Grady, Chad","Address":"2226 Elliott Ave., #410","city":"Seattle","state":"WA","Zip":"98121","Contribution Type":"Paypal","Amount":25.0,"Date of Receipt":"3\/11\/2012"},{"Candidate Name":"Gregory Cendana ","Contributor":"Thompson, Rebecca","Address":"n\/a","city":"Washington","state":"DC","Zip":"00000","Contribution Type":"Paypal","Amount":25.0,"Date of Receipt":"3\/11\/2012"},{"Candidate Name":"Gregory Cendana ","Contributor":"Dzak, Phillip","Address":"n\/a","city":"Washington","state":"DC","Zip":"00000","Contribution Type":"Paypal","Amount":25.0,"Date of Receipt":"3\/11\/2012"},{"Candidate Name":"Gregory Cendana ","Contributor":"Ramirez, Fernando","Address":"n\/a","city":"Washington","state":"DC","Zip":"00000","Contribution Type":"Paypal","Amount":60.0,"Date of Receipt":"3\/11\/2012"},{"Candidate Name":"Gregory Cendana ","Contributor":"Yeh, Alviria","Address":"n\/a","city":"Washington","state":"DC","Zip":"20000","Contribution Type":"Paypal","Amount":25.0,"Date of Receipt":"3\/11\/2012"},{"Candidate Name":"Gregory Cendana ","Contributor":"Okelo, Atieno","Address":"n\/a","city":"Washington","state":"DC","Zip":"00000","Contribution Type":"Paypal","Amount":25.0,"Date of Receipt":"3\/11\/2012"},{"Candidate Name":"Gregory Cendana ","Contributor":"Beatty, Julia","Address":"n\/a","city":"Washington","state":"DC","Zip":"00000","Contribution Type":"Paypal","Amount":50.0,"Date of Receipt":"3\/11\/2012"},{"Candidate Name":"Gregory Cendana ","Contributor":"Chen, Bruce","Address":"n\/a","city":"Washington","state":"DC","Zip":"00000","Contribution Type":"Paypal","Amount":25.0,"Date of Receipt":"3\/11\/2012"},{"Candidate Name":"Gregory Cendana ","Contributor":"Foote, Douglas","Address":"n\/a","city":"Washington","state":"DC","Zip":"20000","Contribution Type":"Paypal","Amount":10.0,"Date of Receipt":"3\/11\/2012"},{"Candidate Name":"Gregory Cendana ","Contributor":"Michaels, Seth","Address":"n\/a","city":"Washington","state":"DC","Zip":"20000","Contribution Type":"Paypal","Amount":25.0,"Date of Receipt":"3\/11\/2012"},{"Candidate Name":"Gregory Cendana ","Contributor":"Gilbart, James","Address":"n\/a","city":"Washington","state":"DC","Zip":"20000","Contribution Type":"Paypal","Amount":25.0,"Date of Receipt":"3\/11\/2012"},{"Candidate Name":"Gregory Cendana ","Contributor":"Shiroma, Darren","Address":"n\/a","city":"Washington","state":"DC","Zip":"20000","Contribution Type":"Paypal","Amount":100.0,"Date of Receipt":"3\/11\/2012"},{"Candidate Name":"Gregory Cendana ","Contributor":"Cheng, Samantha","Address":"n\/a","city":"Washington","state":"DC","Zip":"20000","Contribution Type":"Paypal","Amount":25.0,"Date of Receipt":"3\/11\/2012"},{"Candidate Name":"Gregory Cendana ","Contributor":"Guera, Joaquin","Address":"n\/a","city":"Washington","state":"DC","Zip":"20000","Contribution Type":"Paypal","Amount":50.0,"Date of Receipt":"3\/11\/2012"},{"Candidate Name":"Gregory Cendana ","Contributor":"Duckett, Edward","Address":"n\/a","city":"Washington","state":"DC","Zip":"20000","Contribution Type":"Paypal","Amount":75.0,"Date of Receipt":"3\/11\/2012"},{"Candidate Name":"Gregory Cendana ","Contributor":"Laverty, Heather","Address":"n\/a","city":"Washington","state":"DC","Zip":"20000","Contribution Type":"paypal","Amount":50.0,"Date of Receipt":"3\/11\/2012"},{"Candidate Name":"Gregory Cendana ","Contributor":"Berkley, Carmen","Address":"n\/a","city":"Washington","state":"DC","Zip":"20000","Contribution Type":"Paypal","Amount":100.0,"Date of Receipt":"3\/11\/2012"},{"Candidate Name":"Gregory Cendana ","Contributor":"Norman, Jane","Address":"n\/a","city":"Washington`","state":"DC","Zip":"20000","Contribution Type":"Paypal","Amount":60.0,"Date of Receipt":"3\/11\/2012"},{"Candidate Name":"Gregory Cendana ","Contributor":"Perez, David","Address":"n\/a","city":"Washington","state":"DC","Zip":"20000","Contribution Type":"Paypal","Amount":20.0,"Date of Receipt":"3\/11\/2012"},{"Candidate Name":"Gregory Cendana ","Contributor":"Shiebior, William","Address":"n\/a","city":"Washington","state":"DC","Zip":"20000","Contribution Type":"Check","Amount":150.0,"Date of Receipt":"3\/11\/2012"},{"Candidate Name":"Gregory Cendana ","Contributor":"Bui, Diana","Address":"n\/a","city":"Washington","state":"DC","Zip":"20000","Contribution Type":"Check","Amount":25.0,"Date of Receipt":"3\/11\/2012"},{"Candidate Name":"Gregory Cendana ","Contributor":"Honda, Mike","Address":"123 E. San Carios St., #531","city":"San Jose","state":"CA","Zip":"95112","Contribution Type":"Paypal","Amount":250.0,"Date of Receipt":"4\/2\/2012"},{"Candidate Name":"Gregory Cendana ","Contributor":"Vu, John","Address":"n\/a","city":"Washington","state":"DC","Zip":"00000","Contribution Type":"Paypal","Amount":111.11,"Date of Receipt":"3\/12\/2012"},{"Candidate Name":"Gregory Cendana ","Contributor":"Carruthers, Charlene","Address":"n\/a","city":"Washington","state":"DC","Zip":"20000","Contribution Type":"Paypal","Amount":25.0,"Date of Receipt":"3\/11\/2012"},{"Candidate Name":"Gregory Cendana ","Contributor":"Vu, Cuc ","Address":"n\/a","city":"Washington","state":"DC","Zip":"20000","Contribution Type":"Paypal","Amount":100.0,"Date of Receipt":"3\/11\/2012"},{"Candidate Name":"Gregory Cendana ","Contributor":"DeGuizman, Benjamin","Address":"n\/a","city":"Washington","state":"DC","Zip":"20000","Contribution Type":"Paypal","Amount":25.0,"Date of Receipt":"3\/11\/2012"},{"Candidate Name":"Gregory Cendana ","Contributor":"Wood, Jennifer","Address":"n\/a","city":"Washington","state":"DC","Zip":"20000","Contribution Type":"Paypal","Amount":30.0,"Date of Receipt":"3\/11\/2012"},{"Candidate Name":"Gregory Cendana ","Contributor":"Uno, Malcolm","Address":"n\/a","city":"Washington","state":"DC","Zip":"20000","Contribution Type":"Paypal","Amount":50.0,"Date of Receipt":"3\/11\/2012"},{"Candidate Name":"Gregory Cendana ","Contributor":"Kekeris, Joseph","Address":"n\/a","city":"Washington","state":"DC","Zip":"20000","Contribution Type":"Paypal","Amount":20.0,"Date of Receipt":"3\/11\/2012"},{"Candidate Name":"Gregory Cendana ","Contributor":"O'Sullivan, Paula-Raye","Address":"n\/a","city":"Washington","state":"DC","Zip":"20000","Contribution Type":"Paypal","Amount":40.0,"Date of Receipt":"3\/11\/2012"},{"Candidate Name":"Gregory Cendana ","Contributor":"Mills, Aisha","Address":"n\/a","city":"Washington","state":"DC","Zip":"20000","Contribution Type":"Paypal","Amount":100.0,"Date of Receipt":"3\/11\/2012"},{"Candidate Name":"Gregory Cendana ","Contributor":"Tein, Andrew","Address":"n\/a","city":"Washington","state":"DC","Zip":"20000","Contribution Type":"paypal","Amount":250.0,"Date of Receipt":"3\/11\/2012"},{"Candidate Name":"Gregory Cendana ","Contributor":"Thibeau, Briana","Address":"n\/a","city":"Washington","state":"DC","Zip":"20000","Contribution Type":"Paypal","Amount":25.0,"Date of Receipt":"3\/11\/2012"},{"Candidate Name":"Gregory Cendana ","Contributor":"Booth, Heather","Address":"n\/a","city":"Washington","state":"DC","Zip":"20000","Contribution Type":"Paypal","Amount":25.0,"Date of Receipt":"3\/11\/2012"},{"Candidate Name":"Gregory Cendana ","Contributor":"Kaoh, Christina","Address":"n\/a","city":"Washington","state":"DC","Zip":"20000","Contribution Type":"Paypal","Amount":20.0,"Date of Receipt":"3\/11\/2012"},{"Candidate Name":"Gregory Cendana ","Contributor":"Mungo, Janelle","Address":"n\/a","city":"Washington","state":"DC","Zip":"20000","Contribution Type":"Paypal","Amount":30.0,"Date of Receipt":"3\/11\/2012"},{"Candidate Name":"Gregory Cendana ","Contributor":"Kutz, Tara","Address":"n\/a","city":"washington","state":"DC","Zip":"20000","Contribution Type":"Paypal","Amount":15.0,"Date of Receipt":"3\/11\/2012"},{"Candidate Name":"Gregory Cendana ","Contributor":"Nguyen, Linda","Address":"n\/a","city":"Washington","state":"DC","Zip":"20000","Contribution Type":"CASH","Amount":250.0,"Date of Receipt":"3\/11\/2012"},{"Candidate Name":"Gregory Cendana ","Contributor":"Chen, Wylie","Address":"1419 Lawrence St., NE","city":"Washington","state":"DC","Zip":"20017","Contribution Type":"CASH","Amount":250.0,"Date of Receipt":"3\/11\/2012"},{"Candidate Name":"Gregory Cendana ","Contributor":"Drego Garcia, Martin","Address":"n\/a","city":"Washington","state":"DC","Zip":"20000","Contribution Type":"Check","Amount":20.0,"Date of Receipt":"3\/11\/2012"},{"Candidate Name":"Gregory Cendana ","Contributor":"Cendana, Gregory","Address":"1910 California Street, NW. #101","city":"Washington","state":"DC","Zip":"20009","Contribution Type":"CASH","Amount":250.0,"Date of Receipt":"3\/11\/2012"}]